{
  "ja": {
    "pageTitle": "春日 裕信のポートフォリオ",
    "headerName": "春日 裕信",
    "profileTitle": "プロフィール",
    "profileContent": "慶應義塾大学大学院 政策・メディア研究科に所属しています。",
    "researchTitle": "研究",
    "researchContent": "ここに研究内容の説明を記述します。",
    "publicationsTitle": "業績",
    "publication1": "発表1...",
    "publication2": "論文1...",
    "educationTitle": "学歴",
    "education1": "城北高等学校",
    "education2":"Cascadia College",
    "education3": "慶應義塾大学 総合政策学部",
    "education4": "慶應義塾大学大学院 政策・メディア研究科",
    "skillsTitle": "スキル",
    "skillsContent": "ここにスキルを記述します。",
    "contactTitle": "連絡先",
    "contactContent": "Email: your.email@example.com",
    "navProfile": "プロフィール",
    "navResearch": "研究",
    "navPublications": "業績",
    "navAwards": "受賞歴",
    "navEducation": "学歴",
    "navSkills": "スキル",
    "navContact": "連絡先",
    "awardsTitle": "受賞歴",
    "award1": "受賞1...",
    "navTeaching": "教育活動",
    "teachingTitle": "教育・指導経験",
    "teaching1": "202X年 - 〇〇 (ティーチングアシスタント)"
  },
  "en": {
    "pageTitle": "Hironobu Kasuga's Portfolio",
    "headerName": "Hironobu Kasuga",
    "profileTitle": "Profile",
    "profileContent": "I am a graduate student at Keio University, Graduate School of Media and Governance.",
    "researchTitle": "Research",
    "researchContent": "Describe your research interests here.",
    "publicationsTitle": "Publications",
    "publication1": "Presentation 1...",
    "publication2": "Paper 1...",
    "educationTitle": "Education",
    "education1": "Johoku High School",
    "education2": "Cascadia College",
    "education3": "Faculty of Policy Management, Keio University",
    "education4": "Graduate School of Media and Governance, Keio University",
    "skillsTitle": "Skills",
    "skillsContent": "Describe your skills here.",
    "contactTitle": "Contact",
    "contactContent": "Email: your.email@example.com",
    "navProfile": "Profile",
    "navResearch": "Research",
    "navPublications": "Publications",
    "navAwards": "Awards",
    "navEducation": "Education",
    "navSkills": "Skills",
    "navContact": "Contact",
    "awardsTitle": "Awards",
    "award1": "Award 1...",
    "navTeaching": "Teaching",
    "teachingTitle": "Teaching & Mentoring",
    "teaching1": "202X - Teaching Assistant, [Course Name]"
  }
}